{"cameraMode":{"drawMode":0,"name":"Shaded","section":"Shading Mode"},"sceneLighting":true,"audioPlay":false,"sceneViewState":{"m_AlwaysRefresh":false,"showFog":true,"showSkybox":true,"showFlares":true,"showImageEffects":true,"showParticleSystems":true,"showVisualEffectGraphs":true,"m_FxEnabled":true},"in2DMode":false,"pivot":{"x":1057.8626708984375,"y":-5.134517192840576,"z":-62.1791877746582},"rotation":{"x":0.02555328793823719,"y":-0.9743964076042175,"z":0.16406486928462983,"w":0.15180498361587525},"size":71.42501831054688,"orthographic":false}